swarm/__init__.py
swarm/core.py
swarm/types.py
swarm/util.py
openai_swarm-0.1.1.dist-info/LICENSE
openai_swarm-0.1.1.dist-info/METADATA
openai_swarm-0.1.1.dist-info/WHEEL
openai_swarm-0.1.1.dist-info/top_level.txt
openai_swarm-0.1.1.dist-info/zip-safe
openai_swarm-0.1.1.dist-info/RECORD
