Metadata-Version: 2.1
Name: openai-swarm
Version: 0.1.1
Summary: A lightweight, stateless multi-agent orchestration framework.
Author: OpenAI Solutions
License: MIT
Requires-Python: >=3.10
License-File: LICENSE
Requires-Dist: numpy
Requires-Dist: openai >=1.33.0
Requires-Dist: pytest
Requires-Dist: requests
Requires-Dist: tqdm
Requires-Dist: pre-commit
Requires-Dist: instructor
